statsbasic/Examples.py
statsbasic/Exercises.py
statsbasic/StatsDetailedTests.py
statsbasic/StatsDetailedTestsHelper.py
statsbasic/__init__.py
statsbasic-0.1.dist-info/DESCRIPTION.rst
statsbasic-0.1.dist-info/METADATA
statsbasic-0.1.dist-info/RECORD
statsbasic-0.1.dist-info/WHEEL
statsbasic-0.1.dist-info/metadata.json
statsbasic-0.1.dist-info/top_level.txt
