Metadata-Version: 2.0
Name: statsbasic
Version: 0.1
Summary: Run Basic Statistical Test with lots of output - emphasys on Learning
Home-page: http://github.com/
Author: Diego
Author-email: dmenin@gmail.com
License: MIT
Platform: UNKNOWN
Requires-Dist: tabulate
